geofeaturekit/__init__.py
geofeaturekit/core/__init__.py
geofeaturekit/core/config.py
geofeaturekit/core/extractor.py
geofeaturekit/core/metrics.py
geofeaturekit/core/models.py
geofeaturekit/exceptions/__init__.py
geofeaturekit/exceptions/errors.py
geofeaturekit/utils/__init__.py
geofeaturekit/utils/area.py
geofeaturekit/utils/formatting.py
geofeaturekit/utils/isochrone.py
geofeaturekit/utils/network.py
geofeaturekit/utils/network_advanced.py
geofeaturekit/utils/poi.py
geofeaturekit/utils/poi_categories.py
geofeaturekit/utils/progress.py
geofeaturekit-0.6.1.dist-info/licenses/LICENSE
geofeaturekit-0.6.1.dist-info/licenses/NOTICE.md
geofeaturekit-0.6.1.dist-info/METADATA
geofeaturekit-0.6.1.dist-info/WHEEL
geofeaturekit-0.6.1.dist-info/top_level.txt
geofeaturekit-0.6.1.dist-info/RECORD
