Metadata-Version: 2.4
Name: geofeaturekit
Version: 0.6.1
Summary: GeoFeatureKit transforms simple coordinates into powerful geospatial insights. Analyze street networks, POI diversity, and spatial patterns with professional progress tracking – no paid APIs or complex setup required.
Home-page: https://github.com/lihangalex/geofeaturekit
Author: Alexander Li
Author-email: lihangalex@pm.me
Project-URL: Bug Tracker, https://github.com/lihangalex/geofeaturekit/issues
Project-URL: Documentation, https://github.com/lihangalex/geofeaturekit#readme
Project-URL: Source Code, https://github.com/lihangalex/geofeaturekit
Classifier: Development Status :: 4 - Beta
Classifier: Intended Audience :: Science/Research
Classifier: License :: OSI Approved :: MIT License
Classifier: Operating System :: OS Independent
Classifier: Programming Language :: Python :: 3
Classifier: Programming Language :: Python :: 3.9
Classifier: Programming Language :: Python :: 3.10
Classifier: Programming Language :: Python :: 3.11
Classifier: Programming Language :: Python :: 3.12
Classifier: Topic :: Scientific/Engineering :: GIS
Requires-Python: >=3.9
License-File: LICENSE
License-File: NOTICE.md
Requires-Dist: osmnx>=1.3.0
Requires-Dist: pandas>=1.5.0
Requires-Dist: geopy>=2.3.0
Requires-Dist: folium>=0.14.0
Requires-Dist: tqdm>=4.65.0
Requires-Dist: networkx>=3.0
Requires-Dist: numpy>=1.24.0
Requires-Dist: node2vec>=0.4.6
Requires-Dist: scikit-learn>=1.0.0
Requires-Dist: scipy>=1.7.0
Requires-Dist: gensim>=4.0.0
Requires-Dist: geopandas>=0.9.0
Requires-Dist: shapely>=1.7.0
Dynamic: author
Dynamic: author-email
Dynamic: classifier
Dynamic: description
Dynamic: description-content-type
Dynamic: home-page
Dynamic: license-file
Dynamic: project-url
Dynamic: requires-dist
Dynamic: requires-python
Dynamic: summary
